sentence_splitter/__init__.py
sentence_splitter/splitter.py
iges_sentence_splitter-0.2.1.dist-info/LICENSE
iges_sentence_splitter-0.2.1.dist-info/METADATA
iges_sentence_splitter-0.2.1.dist-info/WHEEL
iges_sentence_splitter-0.2.1.dist-info/top_level.txt
iges_sentence_splitter-0.2.1.dist-info/RECORD
