Metadata-Version: 2.1
Name: iges-sentence-splitter
Version: 0.2.1
Summary: A package for sentence splitting using a pre-trained transformer model.
Home-page: UNKNOWN
Author: Kathryn Chapman
Author-email: kathryn.chapman@iges.com
License: UNKNOWN
Platform: UNKNOWN
Classifier: Programming Language :: Python :: 3
Classifier: License :: OSI Approved :: MIT License
Classifier: Operating System :: OS Independent
Requires-Python: >=3.6
Requires-Dist: torch
Requires-Dist: transformers
